luz/__init__.py
luz/callbacks.py
luz/datasets.py
luz/learner.py
luz/loggers.py
luz/metrics.py
luz/modules.py
luz/runner.py
luz/scorers.py
luz/transforms.py
luz/tuners.py
luz/utils.py
luz-10.3.0.dist-info/LICENSE
luz-10.3.0.dist-info/WHEEL
luz-10.3.0.dist-info/METADATA
luz-10.3.0.dist-info/RECORD
