Metadata-Version: 2.1
Name: luz
Version: 10.3.0
Summary: Lightweight framework for structuring arbitrary reproducible neural network learning procedures using PyTorch.
Home-page: https://github.com/kijanac/luz
License: MIT
Author: Ki-Jana Carter
Author-email: kijana@mit.edu
Requires-Python: >=3.9,<3.11
Classifier: License :: OSI Approved :: MIT License
Classifier: Programming Language :: Python :: 3
Classifier: Programming Language :: Python :: 3.10
Classifier: Programming Language :: Python :: 3.9
Requires-Dist: matplotlib (>=3.3.2,<4.0.0)
Requires-Dist: pyee (>=9.0.3,<10.0.0)
Requires-Dist: scipy (>=1.7.2,<2.0.0)
Requires-Dist: torch (>=1.7.0,<2.0.0)
Project-URL: Repository, https://github.com/kijanac/luz
